sevenbridges/__init__.py
sevenbridges/api.py
sevenbridges/config.py
sevenbridges/decorators.py
sevenbridges/errors.py
sevenbridges/version.py
sevenbridges/http/__init__.py
sevenbridges/http/client.py
sevenbridges/http/error_handlers.py
sevenbridges/meta/__init__.py
sevenbridges/meta/collection.py
sevenbridges/meta/comp_mutable_dict.py
sevenbridges/meta/data.py
sevenbridges/meta/fields.py
sevenbridges/meta/resource.py
sevenbridges/meta/transformer.py
sevenbridges/models/__init__.py
sevenbridges/models/actions.py
sevenbridges/models/app.py
sevenbridges/models/async_jobs.py
sevenbridges/models/automation.py
sevenbridges/models/billing_analysis_breakdown.py
sevenbridges/models/billing_egress_breakdown.py
sevenbridges/models/billing_group.py
sevenbridges/models/billing_storage_breakdown.py
sevenbridges/models/bulk.py
sevenbridges/models/dataset.py
sevenbridges/models/division.py
sevenbridges/models/drs_import.py
sevenbridges/models/endpoints.py
sevenbridges/models/enums.py
sevenbridges/models/execution_details.py
sevenbridges/models/file.py
sevenbridges/models/invoice.py
sevenbridges/models/link.py
sevenbridges/models/marker.py
sevenbridges/models/member.py
sevenbridges/models/project.py
sevenbridges/models/rate_limit.py
sevenbridges/models/storage_export.py
sevenbridges/models/storage_import.py
sevenbridges/models/task.py
sevenbridges/models/team.py
sevenbridges/models/team_member.py
sevenbridges/models/user.py
sevenbridges/models/volume.py
sevenbridges/models/compound/__init__.py
sevenbridges/models/compound/analysis_cost.py
sevenbridges/models/compound/analysis_cost_breakdown.py
sevenbridges/models/compound/egress_cost.py
sevenbridges/models/compound/error.py
sevenbridges/models/compound/import_result.py
sevenbridges/models/compound/measurement.py
sevenbridges/models/compound/price.py
sevenbridges/models/compound/price_breakdown.py
sevenbridges/models/compound/billing/__init__.py
sevenbridges/models/compound/billing/invoice_period.py
sevenbridges_python-2.11.1.dist-info/LICENCE
sevenbridges_python-2.11.1.dist-info/METADATA
sevenbridges_python-2.11.1.dist-info/WHEEL
sevenbridges_python-2.11.1.dist-info/top_level.txt
sevenbridges_python-2.11.1.dist-info/RECORD
