Metadata-Version: 2.1
Name: sevenbridges-python
Version: 2.11.1
Summary: SBG API python client bindings
Home-page: https://github.com/sbg/sevenbridges-python
Maintainer: Seven Bridges Genomics Inc.
Maintainer-email: dejan.knezevic@sbgenomics.com
License: Apache Software License 2.0
Keywords: sevenbridges,sbg,api,cgc,cancer,genomics,cloud
Platform: Windows
Platform: POSIX
Platform: MacOS
Classifier: License :: OSI Approved :: Apache Software License
Classifier: Operating System :: OS Independent
Classifier: Programming Language :: Python
Classifier: Programming Language :: Python :: 3
Classifier: Topic :: Software Development
Classifier: Topic :: Scientific/Engineering :: Bio-Informatics
Classifier: Topic :: Software Development :: Libraries :: Python Modules
License-File: LICENCE
Requires-Dist: requests>=2.25.1
Requires-Dist: urllib3>=1.26.2
